LICENSE.txt
MANIFEST.in
README.rst
setup.cfg
setup.py
alphaver/__init__.py
alphaver/__main__.py
alphaver/divyansh.py
alphaver/divyansh2.py
alphaver/divyansh3.py
alphaver.egg-info/PKG-INFO
alphaver.egg-info/SOURCES.txt
alphaver.egg-info/dependency_links.txt
alphaver.egg-info/requires.txt
alphaver.egg-info/top_level.txt