Metadata-Version: 1.1
Name: alphaver
Version: 0.5.5
Summary: Alpha version for cg_acc
Home-page: https://github.com/Avikalp7/CG-Accumulator
Author: Unknown
Author-email: avikalp22@gmail.com
License: MIT
Keywords: testing,cg_acc,example
Platform: UNKNOWN
Classifier: Development Status :: 3 - Alpha
Classifier: Intended Audience :: Developers
Classifier: License :: OSI Approved :: MIT License
Classifier: Programming Language :: Python :: 2.7
